{
  "index": 1,
  "id": "5dc0a02703df51fc0bca37ca",
  "title": "Sint aliquip culpa excepteur labore eiusmod ad.",
  "type": "object",
  "dates": [
    {
      "begin": "1940-05-26",
      "end": "1974-10-22",
      "expression": "May 26th, 1940 - Oct 22nd, 1974",
      "type": "bulk",
      "label": "copyright"
    },
    {
      "begin": "1917-04-06",
      "end": "2013-08-15",
      "expression": "Apr 6th, 1917 - Aug 15th, 2013",
      "type": "inclusive",
      "label": "copyright"
    },
    {
      "begin": "1941-02-19",
      "end": "1965-10-21",
      "expression": "Feb 19th, 1941 - Oct 21st, 1965",
      "type": "bulk",
      "label": "deaccession"
    }
  ],
  "extents": [
    {
      "value": "5.93",
      "type": "cassettes"
    }
  ],
  "notes": [],
  "terms": [],
  "agents": [
    {
      "external_identifiers": [
        {
          "source": "archivesspace",
          "identifier": "/agents_person/3"
        }
      ]
    }
  ],
  "languages": [
    {
      "expression": "Spanish",
      "identifier": "spa"
    }
  ],
  "rights_statements": [],
  "ancestors": [
    {
      "external_identifiers": [
        {
          "source": "archivesspace",
          "identifier": "/repositories/2/resources/1"
        }
      ]
    }
  ],
  "external_identifiers": [
    {
      "source": "archivesspace",
      "identifier": "/repositories/2/archival_objects/1"
    }
  ]
}